aiohttp_scraper/__init__.py
aiohttp_scraper/exceptions.py
aiohttp_scraper/proxies.py
aiohttp_scraper/scripts/.gitignore
aiohttp_scraper/scripts/__init__.py
aiohttp_scraper/session.py
aiohttp_scraper/user_agents.py
aiohttp_scraper-0.1.4.dist-info/LICENSE
aiohttp_scraper-0.1.4.dist-info/WHEEL
aiohttp_scraper-0.1.4.dist-info/METADATA
aiohttp_scraper-0.1.4.dist-info/RECORD
